foxcli/__init__.py
foxcli/arg_accessor.py
foxcli/argument.py
foxcli/cli.py
foxcli/command.py
foxcli/command_context.py
foxcli/command_info.py
foxcli/command_registry.py
foxcli/option.py
foxcli/parsed_command.py
foxcli-0.6.0.dist-info/METADATA
foxcli-0.6.0.dist-info/WHEEL
foxcli-0.6.0.dist-info/licenses/LICENSE
foxcli-0.6.0.dist-info/RECORD
