Metadata-Version: 2.4
Name: foxcli
Version: 0.6.0
Summary: A lightweight and minimal CLI framework
Project-URL: Repository, https://github.com/depthbomb/foxcli
Project-URL: Issues, https://github.com/depthbomb/foxcli/issues
Project-URL: Changelog, https://github.com/depthbomb/foxcli/blob/master/CHANGELOG.md
Author: depthbomb
License: MIT
License-File: LICENSE
Keywords: cli,framework
Classifier: Development Status :: 4 - Beta
Classifier: Intended Audience :: Developers
Classifier: License :: OSI Approved :: MIT License
Classifier: Natural Language :: English
Classifier: Operating System :: OS Independent
Classifier: Programming Language :: Python :: 3
Classifier: Programming Language :: Python :: 3 :: Only
Classifier: Topic :: Software Development
Classifier: Topic :: Software Development :: Libraries
Classifier: Topic :: Software Development :: Libraries :: Application Frameworks
Classifier: Topic :: Software Development :: Libraries :: Python Modules
Classifier: Topic :: Terminals
Classifier: Typing :: Typed
Requires-Python: >=3.12
